harp/__init__.py
harp/appdata.py
harp/autofill.py
harp/batch.py
harp/config.py
harp/errorcheck.py
harp/getpickle.py
harp/manualcrop.py
harp/processing.py
harp/queuejob.py
harp/run_harp.py
harp/setup_HARP.py
harp/version.py
harp/imgprocessing/__init__.py
harp/imgprocessing/compress.py
harp/imgprocessing/crop.py
harp/imgprocessing/io_.py
harp/imgprocessing/orientations.py
harp/imgprocessing/resampler.py
harp/imgprocessing/test_compress.py
harp/imgprocessing/zproject.py
harp/ui/__init__.py
harp/ui/mainwindow.py
harp/ui/mainwindow_new.py
harp_image_preprocess-2.4.0.4.dist-info/DESCRIPTION.rst
harp_image_preprocess-2.4.0.4.dist-info/METADATA
harp_image_preprocess-2.4.0.4.dist-info/RECORD
harp_image_preprocess-2.4.0.4.dist-info/WHEEL
harp_image_preprocess-2.4.0.4.dist-info/entry_points.txt
harp_image_preprocess-2.4.0.4.dist-info/metadata.json
harp_image_preprocess-2.4.0.4.dist-info/top_level.txt
