Metadata-Version: 2.0
Name: harp-image-preprocess
Version: 2.4.0.4
Summary: Cross-platform application for automating the processing of μCT and OPT image data.
Home-page: https://github.com/mpi2/HARP
Author: BIT Team MRC harwell
Author-email: bit@har.mrc.ac.uk
License: Apache2
Keywords: image processing,micro-CT
Platform: UNKNOWN
Classifier: Programming Language :: Python :: 3
Classifier: License :: OSI Approved :: MIT License
Classifier: Operating System :: OS Independent
Requires-Dist: numpy (>=1.19.0)
Requires-Dist: logzero (>=1.5.0)
Requires-Dist: matplotlib (>=3.3.0)
Requires-Dist: scikit-image (>=0.17.2)
Requires-Dist: opencv-python
Requires-Dist: Image (>=1.5.33)
Requires-Dist: Pillow (>=8.0.1)
Requires-Dist: PyQt5 (==5.14.2)
Requires-Dist: PyYAML (>=5.3.1)
Requires-Dist: SimpleITK (>=1.2.0)
Requires-Dist: strconv (>=0.4.2)
Requires-Dist: pynrrd
Requires-Dist: appdirs
Requires-Dist: tifffile
